Metadata-Version: 2.4
Name: iflow-mcp_youtube-mcp
Version: 0.1.1
Summary: YouTube MCP Server for video analysis with Gemini AI
Home-page: https://github.com/Prajwal-ak-0/youtube-mcp
Author: Prajwal-ak-0
License: MIT
Project-URL: Homepage, https://github.com/Prajwal-ak-0/youtube-mcp
Project-URL: Bug Tracker, https://github.com/Prajwal-ak-0/youtube-mcp/issues
Keywords: youtube,mcp,ai,gemini,transcript
Classifier: Programming Language :: Python :: 3
Classifier: Programming Language :: Python :: 3.9
Classifier: Programming Language :: Python :: 3.10
Classifier: Programming Language :: Python :: 3.11
Classifier: Topic :: Software Development :: Libraries :: Python Modules
Requires-Python: >=3.9
Requires-Dist: mcp
Requires-Dist: google-genai
Requires-Dist: aiohttp
Requires-Dist: youtube-transcript-api
Requires-Dist: python-dotenv
Dynamic: home-page
Dynamic: requires-python
